topsis_jatin_102218046/__init__.py
topsis_jatin_102218046/topsis.py
topsis_jatin_102218046-0.1.dist-info/LICENSE
topsis_jatin_102218046-0.1.dist-info/METADATA
topsis_jatin_102218046-0.1.dist-info/WHEEL
topsis_jatin_102218046-0.1.dist-info/entry_points.txt
topsis_jatin_102218046-0.1.dist-info/top_level.txt
topsis_jatin_102218046-0.1.dist-info/RECORD
