Metadata-Version: 2.1
Name: topsis-jatin-102218046
Version: 0.1
Summary: A Python package for TOPSIS method
Author: Jatin Sharma
Author-email: jatinsh596@gmail.com
Classifier: Programming Language :: Python :: 3
Classifier: License :: OSI Approved :: MIT License
Classifier: Operating System :: OS Independent
Requires-Python: >=3.6
License-File: LICENSE
Requires-Dist: numpy
Requires-Dist: pandas
